smsutil/__init__.py
smsutil/__version__.py
smsutil/codecs.py
smsutil-1.1.3.dist-info/LICENSE.txt
smsutil-1.1.3.dist-info/METADATA
smsutil-1.1.3.dist-info/WHEEL
smsutil-1.1.3.dist-info/top_level.txt
smsutil-1.1.3.dist-info/RECORD
