Metadata-Version: 2.1
Name: smsutil
Version: 1.1.3
Summary: encode, decode and split SMS.
Home-page: https://github.com/jezeniel/smsutil
Author: Jezeniel Zapanta
Author-email: jezeniel.zapanta@gmail.com
License: MIT
Keywords: sms utils utilities smsutil short message service
Platform: UNKNOWN
Classifier: Intended Audience :: Developers
Classifier: Intended Audience :: Telecommunications Industry
Classifier: License :: OSI Approved :: MIT License
Classifier: Programming Language :: Python :: 2.7
Classifier: Programming Language :: Python :: 3.6
Classifier: Programming Language :: Python :: 3.7
Classifier: Programming Language :: Python :: 3.8
Classifier: Topic :: Software Development :: Libraries
Requires-Dist: future (>=0.16.0)
